{"assets/fonts/Poppins-Black.ttf":["assets/fonts/Poppins-Black.ttf"],"assets/fonts/Poppins-BlackItalic.ttf":["assets/fonts/Poppins-BlackItalic.ttf"],"assets/fonts/Poppins-Bold.ttf":["assets/fonts/Poppins-Bold.ttf"],"assets/fonts/Poppins-BoldItalic.ttf":["assets/fonts/Poppins-BoldItalic.ttf"],"assets/fonts/Poppins-ExtraBold.ttf":["assets/fonts/Poppins-ExtraBold.ttf"],"assets/fonts/Poppins-ExtraBoldItalic.ttf":["assets/fonts/Poppins-ExtraBoldItalic.ttf"],"assets/fonts/Poppins-ExtraLight.ttf":["assets/fonts/Poppins-ExtraLight.ttf"],"assets/fonts/Poppins-ExtraLightItalic.ttf":["assets/fonts/Poppins-ExtraLightItalic.ttf"],"assets/fonts/Poppins-Italic.ttf":["assets/fonts/Poppins-Italic.ttf"],"assets/fonts/Poppins-Light.ttf":["assets/fonts/Poppins-Light.ttf"],"assets/fonts/Poppins-LightItalic.ttf":["assets/fonts/Poppins-LightItalic.ttf"],"assets/fonts/Poppins-Medium.ttf":["assets/fonts/Poppins-Medium.ttf"],"assets/fonts/Poppins-MediumItalic.ttf":["assets/fonts/Poppins-MediumItalic.ttf"],"assets/fonts/Poppins-Regular.ttf":["assets/fonts/Poppins-Regular.ttf"],"assets/fonts/Poppins-SemiBold.ttf":["assets/fonts/Poppins-SemiBold.ttf"],"assets/fonts/Poppins-SemiBoldItalic.ttf":["assets/fonts/Poppins-SemiBoldItalic.ttf"],"assets/fonts/Poppins-Thin.ttf":["assets/fonts/Poppins-Thin.ttf"],"assets/images/company/apps.png":["assets/images/company/apps.png"],"assets/images/company/remote.png":["assets/images/company/remote.png"],"assets/images/company/rizz.jpeg":["assets/images/company/rizz.jpeg"],"assets/images/company/verdant.png":["assets/images/company/verdant.png"],"assets/images/company/zaptech.png":["assets/images/company/zaptech.png"],"assets/images/jiffy/jiffy1.jpeg":["assets/images/jiffy/jiffy1.jpeg"],"assets/images/jiffy/jiffy2.jpeg":["assets/images/jiffy/jiffy2.jpeg"],"assets/images/jiffy/jiffy3.jpeg":["assets/images/jiffy/jiffy3.jpeg"],"assets/images/memow/memow1.jpeg":["assets/images/memow/memow1.jpeg"],"assets/images/memow/memow2.jpeg":["assets/images/memow/memow2.jpeg"],"assets/images/memow/memow3.jpeg":["assets/images/memow/memow3.jpeg"],"assets/images/petto/petto1.jpeg":["assets/images/petto/petto1.jpeg"],"assets/images/petto/petto2.jpeg":["assets/images/petto/petto2.jpeg"],"assets/images/petto/petto3.jpeg":["assets/images/petto/petto3.jpeg"],"assets/images/rizz/rizz1.jpeg":["assets/images/rizz/rizz1.jpeg"],"assets/images/rizz/rizz2.jpeg":["assets/images/rizz/rizz2.jpeg"],"assets/images/rizz/rizz3.jpeg":["assets/images/rizz/rizz3.jpeg"],"assets/images/techstacks/Android.png":["assets/images/techstacks/Android.png"],"assets/images/techstacks/Dotnet.png":["assets/images/techstacks/Dotnet.png"],"assets/images/techstacks/Flutter.png":["assets/images/techstacks/Flutter.png"],"assets/images/techstacks/apple.png":["assets/images/techstacks/apple.png"],"assets/images/techstacks/backend.png":["assets/images/techstacks/backend.png"],"assets/images/techstacks/cloud.png":["assets/images/techstacks/cloud.png"],"assets/images/techstacks/web.png":["assets/images/techstacks/web.png"],"assets/images/techstacks/windows.png":["assets/images/techstacks/windows.png"],"assets/images/tennis/tennis1.jpeg":["assets/images/tennis/tennis1.jpeg"],"assets/images/tennis/tennis2.jpeg":["assets/images/tennis/tennis2.jpeg"],"assets/images/tennis/tennis3.jpeg":["assets/images/tennis/tennis3.jpeg"],"packages/cupertino_icons/assets/CupertinoIcons.ttf":["packages/cupertino_icons/assets/CupertinoIcons.ttf"],"packages/font_awesome_flutter/lib/fonts/fa-brands-400.ttf":["packages/font_awesome_flutter/lib/fonts/fa-brands-400.ttf"],"packages/font_awesome_flutter/lib/fonts/fa-regular-400.ttf":["packages/font_awesome_flutter/lib/fonts/fa-regular-400.ttf"],"packages/font_awesome_flutter/lib/fonts/fa-solid-900.ttf":["packages/font_awesome_flutter/lib/fonts/fa-solid-900.ttf"]}